serial_midi_bridge/__init__.py
serial_midi_bridge/serial_midi_bridge.py
serial_midi_bridge-1.0.1.dist-info/licenses/LICENSE
serial_midi_bridge-1.0.1.dist-info/METADATA
serial_midi_bridge-1.0.1.dist-info/WHEEL
serial_midi_bridge-1.0.1.dist-info/entry_points.txt
serial_midi_bridge-1.0.1.dist-info/top_level.txt
serial_midi_bridge-1.0.1.dist-info/RECORD
