Metadata-Version: 2.4
Name: serial-midi-bridge
Version: 1.0.1
Summary: A bridge for serial devices and MIDI controllers
Author: esophagoose
License-Expression: Apache-2.0
Project-URL: Repository, https://github.com/esophagoose/serial_midi_bridge
Keywords: MIDI,multimedia,music,serial,UART
Classifier: Development Status :: 4 - Beta
Classifier: Programming Language :: Python :: 3
Classifier: Programming Language :: Python :: 3.6
Classifier: Programming Language :: Python :: 3.7
Classifier: Programming Language :: Python :: 3.8
Classifier: Programming Language :: Python :: 3.9
Classifier: Topic :: Multimedia :: Sound/Audio :: MIDI
Requires-Python: >=3.7
License-File: LICENSE
Requires-Dist: pyserial==3.5
Requires-Dist: python-rtmidi==1.5.8
Dynamic: license-file
